sphinxext/mimictoc.py
sphinxext_mimic-0.1.1.dist-info/LICENSE.md
sphinxext_mimic-0.1.1.dist-info/METADATA
sphinxext_mimic-0.1.1.dist-info/WHEEL
sphinxext_mimic-0.1.1.dist-info/top_level.txt
sphinxext_mimic-0.1.1.dist-info/RECORD
